frankensync/__init__.py
frankensync/core.py
frankensync/transformers.py
frankensync/utils/__init__.py
frankensync/utils/markers.py
frankensync-0.0.0.dist-info/WHEEL
frankensync-0.0.0.dist-info/METADATA
frankensync-0.0.0.dist-info/RECORD
