Metadata-Version: 2.1
Name: frankensync
Version: 0.0.0
Summary: 
Author: Dylan Wilson
Author-email: dylanjw@protonmail.com
Requires-Python: >=3.6,<3.9
Classifier: Programming Language :: Python :: 3
Classifier: Programming Language :: Python :: 3.6
Classifier: Programming Language :: Python :: 3.7
Classifier: Programming Language :: Python :: 3.8
Requires-Dist: astor (>=0.8,<0.9)
Requires-Dist: toolz (>=0.10,<0.11)
